CHANGES.txt
LICENSE.txt
MANIFEST.in
README.rst
setup.cfg
setup.py
munin_plugins/__init__.py
munin_plugins/base_info.py
munin_plugins/env.py
munin_plugins/generate.py
munin_plugins.egg-info/PKG-INFO
munin_plugins.egg-info/SOURCES.txt
munin_plugins.egg-info/dependency_links.txt
munin_plugins.egg-info/entry_points.txt
munin_plugins.egg-info/not-zip-safe
munin_plugins.egg-info/requires.txt
munin_plugins.egg-info/top_level.txt
munin_plugins/checks/00-interpreter.py
munin_plugins/checks/10-psutil.py
munin_plugins/checks/20-cache.py
munin_plugins/checks/__init__.py
munin_plugins/plugins/__init__.py
munin_plugins/plugins/plugin.py
munin_plugins/plugins/snsr_apache.py
munin_plugins/plugins/snsr_errfiles.py
munin_plugins/plugins/snsr_monit.py
munin_plugins/plugins/snsr_nginx.py
munin_plugins/plugins/snsr_processes.py
munin_plugins/plugins/snsr_repmgr.py
munin_plugins/plugins/processes_analyzers/__init__.py
munin_plugins/plugins/processes_analyzers/base.py
munin_plugins/plugins/processes_analyzers/connections.py
munin_plugins/plugins/processes_analyzers/cpu.py
munin_plugins/plugins/processes_analyzers/ios.py
munin_plugins/plugins/processes_analyzers/memory.py
munin_plugins/plugins/processes_analyzers/storage.py
munin_plugins/plugins/processes_analyzers/swap.py
munin_plugins/plugins/processes_analyzers/threads.py
munin_plugins/plugins/www_analyzers/__init__.py
munin_plugins/plugins/www_analyzers/base.py
munin_plugins/plugins/www_analyzers/botscounter.py
munin_plugins/plugins/www_analyzers/httpcodescounter.py
munin_plugins/plugins/www_analyzers/latencyaggregator.py
munin_plugins/plugins/www_analyzers/sizeaggregator.py
munin_plugins/utils/__init__.py
munin_plugins/utils/caches.py
munin_plugins/utils/config.py
munin_plugins/utils/parsers.py