Metadata-Version: 1.1
Name: munin-plugins
Version: 5.1
Summary: Sensors for munin
Home-page: https://github.com/cippino/munin_plugins
Author: Cippino
Author-email: cippinofg <at> gmail <dot> com
License: LICENSE.txt
Keywords: apache monit nginx plone java repmgr munin sensors
Platform: UNKNOWN
Classifier: Development Status :: 5 - Production/Stable
Classifier: Intended Audience :: System Administrators
Classifier: Programming Language :: Python :: 2.7
Classifier: Topic :: System :: Monitoring
Classifier: Topic :: System :: Systems Administration
